pubmedparser/__init__.py
pubmedparser/_readxml.c
pubmedparser/_readxml.pyi
pubmedparser/ftp.py
pubmedparser/storage.py
pubmedparser/_readxml.cpython-310-darwin.so
pubmedparser2-2.1.2.dist-info/LICENSE
pubmedparser2-2.1.2.dist-info/METADATA
pubmedparser2-2.1.2.dist-info/WHEEL
pubmedparser2-2.1.2.dist-info/RECORD
