Metadata-Version: 2.1
Name: pubmedparser2
Version: 2.1.2
Summary: Download and parse pubmed publication data
Home-page: https://github.com/net-synergy/pubmedparser
License: MIT
Keywords: publication,network,MEDLINE,PubMed,references
Author: David Connell
Author-email: davidconnell12@gmail.com
Maintainer: David Connell
Maintainer-email: davidconnell12@gmail.com
Requires-Python: >=3.10,<4.0
Classifier: License :: OSI Approved :: MIT License
Classifier: Programming Language :: Python :: 3
Classifier: Programming Language :: Python :: 3.10
Classifier: Programming Language :: Python :: 3.11
Classifier: Programming Language :: Python :: 3.12
Classifier: Programming Language :: Python :: 3.13
Requires-Dist: appdirs (>=1.4.4,<2.0.0)
Requires-Dist: psutil (>=6.1.0,<7.0.0)
Project-URL: Repository, https://github.com/net-synergy/pubmedparser
